cryptlock/__init__.py
cryptlock/cli.py
cryptlock-1.1.1.dist-info/METADATA
cryptlock-1.1.1.dist-info/WHEEL
cryptlock-1.1.1.dist-info/entry_points.txt
cryptlock-1.1.1.dist-info/top_level.txt
cryptlock-1.1.1.dist-info/RECORD
